{
    "data": [
        {
            "Description": "<img src='https://github.githubassets.com/images/icons/emoji/unicode/1f4a1.png?v8'>  A light Swift wrapper around Objective-C Runtime", 
            "Forks": 3, 
            "Language": "Swift", 
            "Repo": "<a href='https://github.com/sushinoya/lumos'target='_blank'>lumos</a>", 
            "Stars": 65
        }, 
        {
            "Description": "Swizzlean, an Objective-C Swizzle Helper Class.", 
            "Forks": 12, 
            "Language": "Objective-C", 
            "Repo": "<a href='https://github.com/rbaumbach/Swizzlean'target='_blank'>Swizzlean</a>", 
            "Stars": 93
        }
    ]
}